mat3ra/__init__.py
mat3ra/code/__init__.py
mat3ra/code/array_with_ids.py
mat3ra/code/constants.py
mat3ra/code/entity.py
mat3ra/code/value_with_id.py
mat3ra/code/vector.py
mat3ra/code/mixins/__init__.py
mat3ra_code-2025.12.22.post0.dist-info/LICENSE.md
mat3ra_code-2025.12.22.post0.dist-info/METADATA
mat3ra_code-2025.12.22.post0.dist-info/WHEEL
mat3ra_code-2025.12.22.post0.dist-info/top_level.txt
mat3ra_code-2025.12.22.post0.dist-info/RECORD
