Metadata-Version: 2.1
Name: mat3ra-code
Version: 2025.12.22.post0
Summary: COre DEfinitions.
Author-email: "Exabyte Inc." <info@mat3ra.com>
License: # LICENSE
Classifier: Programming Language :: Python
Classifier: Programming Language :: Python :: 3
Classifier: Development Status :: 3 - Alpha
Classifier: Topic :: Software Development
Requires-Python: >=3.8
License-File: LICENSE.md
Requires-Dist: numpy
Requires-Dist: jsonschema >=2.6.0
Requires-Dist: pydantic >=2.7.1
Requires-Dist: mat3ra-esse
Requires-Dist: mat3ra-utils
Provides-Extra: all
Requires-Dist: mat3ra-code[tests] ; extra == 'all'
Provides-Extra: tests
Requires-Dist: coverage[toml] >=5.3 ; extra == 'tests'
Requires-Dist: pre-commit ; extra == 'tests'
Requires-Dist: black ; extra == 'tests'
Requires-Dist: ruff ; extra == 'tests'
Requires-Dist: isort ; extra == 'tests'
Requires-Dist: mypy ; extra == 'tests'
Requires-Dist: pip-tools ; extra == 'tests'
Requires-Dist: pytest ; extra == 'tests'
Requires-Dist: pytest-cov ; extra == 'tests'
